penify_hook/__init__.py
penify_hook/api_client.py
penify_hook/base_analyzer.py
penify_hook/commit_analyzer.py
penify_hook/config_command.py
penify_hook/constants.py
penify_hook/file_analyzer.py
penify_hook/folder_analyzer.py
penify_hook/git_analyzer.py
penify_hook/jira_client.py
penify_hook/llm_client.py
penify_hook/login_command.py
penify_hook/main.py
penify_hook/ui_utils.py
penify_hook/utils.py
penifycli-0.2.4.dist-info/METADATA
penifycli-0.2.4.dist-info/WHEEL
penifycli-0.2.4.dist-info/entry_points.txt
penifycli-0.2.4.dist-info/top_level.txt
penifycli-0.2.4.dist-info/RECORD
