Metadata-Version: 2.2
Name: penifycli
Version: 0.2.4
Summary: A penify cli tool to generate Documentation, Commit-summary.
Home-page: https://github.com/SingularityX-ai/penifycli
Author: Suman Saurabh
Author-email: ss.sumansaurabh92@gmail.com
Classifier: Programming Language :: Python :: 3
Classifier: License :: OSI Approved :: MIT License
Classifier: Operating System :: OS Independent
Requires-Python: >=3.6
Requires-Dist: requests
Requires-Dist: tqdm
Requires-Dist: GitPython
Requires-Dist: colorama
Requires-Dist: litellm
Requires-Dist: jira
Dynamic: author
Dynamic: author-email
Dynamic: classifier
Dynamic: description
Dynamic: description-content-type
Dynamic: home-page
Dynamic: requires-dist
Dynamic: requires-python
Dynamic: summary
